remembering/DSC_1033.JPG
remembering/__init__.py
remembering/__main__.py
remembering/db.py
remembering/model.py
remembering/model_old.py
remembering/rg_global.py
remembering/timer.py
remembering/version.txt
remembering/gui/__init__.py
remembering/gui/breathing_dlg.py
remembering/gui/details_cw.py
remembering/gui/launch_actions.py
remembering/gui/mc_global.py
remembering/gui/old_code
remembering/gui/settings_win.py
remembering/gui/unused_notification_dlg.py
remembering-0.0.1.dist-info/LICENSE.txt
remembering-0.0.1.dist-info/METADATA
remembering-0.0.1.dist-info/WHEEL
remembering-0.0.1.dist-info/entry_points.txt
remembering-0.0.1.dist-info/top_level.txt
remembering-0.0.1.dist-info/RECORD
