Metadata-Version: 2.1
Name: remembering
Version: 0.0.1
Summary: Remembering is a reminder application for things we'd like to stay aware of during the day when using the computer
Author-email: Tord Dellsén <tord.dellsen@gmail.com>
License: GNU GENERAL PUBLIC LICENSE
Project-URL: GitLab, https://gitlab.com/SunyataZero/remembering/
Keywords: self-care
Classifier: License :: OSI Approved :: GNU General Public License v3 (GPLv3)
Classifier: Programming Language :: Python
Classifier: Programming Language :: Python :: 3
Classifier: Development Status :: 2 - Pre-Alpha
Classifier: Intended Audience :: End Users/Desktop
Classifier: Topic :: Other/Nonlisted Topic
Requires-Python: >=3.8
License-File: LICENSE.txt
Requires-Dist: PySide6 (>=6.0)
Provides-Extra: dev
Requires-Dist: build ; extra == 'dev'
Requires-Dist: wheel ; extra == 'dev'
Requires-Dist: twine ; extra == 'dev'
Requires-Dist: pyinstaller ; extra == 'dev'
Requires-Dist: pytest ; extra == 'dev'
Requires-Dist: pytest-qt ; extra == 'dev'
Requires-Dist: pytest-xvfb ; extra == 'dev'
Requires-Dist: coverage ; extra == 'dev'
Requires-Dist: mypy ; extra == 'dev'
Requires-Dist: prospector[with_everything] ; extra == 'dev'
